__init__.py
cleanpycache/__init__.py
cleanpycache/cleanpycache.py
cleanpycache/cli.py
cleanpycache-0.1.2.dist-info/LICENSE
cleanpycache-0.1.2.dist-info/METADATA
cleanpycache-0.1.2.dist-info/WHEEL
cleanpycache-0.1.2.dist-info/entry_points.txt
cleanpycache-0.1.2.dist-info/top_level.txt
cleanpycache-0.1.2.dist-info/RECORD
