Metadata-Version: 2.1
Name: cleanpycache
Version: 0.1.2
Summary: Multiple ways to clean __pycache__ folders recursively from a specified root path
Author-email: Ed Waldner <waldevburry@proton.me>
Maintainer-email: Ed Waldner <waldevburry@proton.me>
Project-URL: Homepage, https://github.com/ew98/cleanpycache
Project-URL: Documentation, https://github.com/ew98/cleanpycache/wiki/CleanPycache
Project-URL: Issues, https://github.com/ew98/cleanpycache/issues
Keywords: util,utility
Classifier: Development Status :: 3 - Alpha
Classifier: Environment :: Console
Classifier: Intended Audience :: Developers
Classifier: License :: OSI Approved :: MIT License
Classifier: Natural Language :: English
Classifier: Programming Language :: Python :: 3.9
Classifier: Programming Language :: Python :: 3.10
Classifier: Programming Language :: Python :: 3.11
Classifier: Operating System :: OS Independent
Classifier: Topic :: Utilities
Requires-Python: >=3.9
License-File: LICENSE
Requires-Dist: argcomplete
Requires-Dist: quickcolor
Requires-Dist: delayviewer
Requires-Dist: showexception
